quasar_client/__init__.py
quasar_client/client.py
quasar_client/dataclasses/classify.py
quasar_client/dataclasses/column_count_classifier.py
quasar_client/dataclasses/coref.py
quasar_client/dataclasses/embed.py
quasar_client/dataclasses/extract.py
quasar_client/dataclasses/layout_element_classifier.py
quasar_client/dataclasses/models.py
quasar_client/dataclasses/rank.py
quasar_client/dataclasses/tag.py
quasar_client/dataclasses/text_line_detect.py
quasar_client/dataclasses/vit_layout_element_classify.py
quasar_client/py.typed
quasar_client/resources/base.py
quasar_client/resources/classifier.py
quasar_client/resources/column_count_classifier.py
quasar_client/resources/coref.py
quasar_client/resources/embed.py
quasar_client/resources/extract.py
quasar_client/resources/multimodal_embed_and_classify.py
quasar_client/resources/rank.py
quasar_client/resources/tagger.py
quasar_client/resources/text_line_detect.py
quasar_client/resources/vit_layout_element_classify.py
quasar_client-0.1.26.dist-info/WHEEL
quasar_client-0.1.26.dist-info/METADATA
quasar_client-0.1.26.dist-info/RECORD
