Metadata-Version: 2.3
Name: quasar-client
Version: 0.1.26
Summary: Legion Intelligence Python ML Inference Client
Requires-Dist: httpx>=0.28.1
Requires-Dist: openai>=2.2.0
Requires-Dist: pydantic>=2.10.6
Requires-Dist: requests>=2.32.4
Requires-Python: >=3.8
